fabric_jumpstart/__init__.py
fabric_jumpstart/constants.py
fabric_jumpstart/core.py
fabric_jumpstart/jumpstart.css
fabric_jumpstart/jumpstart.js
fabric_jumpstart/registry.yml
fabric_jumpstart/response.css
fabric_jumpstart/response.py
fabric_jumpstart/ui.py
fabric_jumpstart/utils.py
fabric_jumpstart/jumpstarts/analytics-lab/assets/image-example.png
fabric_jumpstart/jumpstarts/analytics-lab/src/parameter.yml
fabric_jumpstart/jumpstarts/analytics-lab/src/1_ExploreData.Notebook/.platform
fabric_jumpstart/jumpstarts/analytics-lab/src/1_ExploreData.Notebook/notebook-content.py
fabric_jumpstart/jumpstarts/analytics-lab/src/SalesAndLogisticsLH.Lakehouse/.platform
fabric_jumpstart/jumpstarts/analytics-lab/src/SalesAndLogisticsLH.Lakehouse/alm.settings.json
fabric_jumpstart/jumpstarts/analytics-lab/src/SalesAndLogisticsLH.Lakehouse/lakehouse.metadata.json
fabric_jumpstart/jumpstarts/analytics-lab/src/SalesAndLogisticsLH.Lakehouse/shortcuts.metadata.json
fabric_jumpstart/ui_assets/app_development_24_color.svg
fabric_jumpstart/ui_assets/copy-icon.svg
fabric_jumpstart/ui_assets/data_engineering_24_color.svg
fabric_jumpstart/ui_assets/data_factory_24_color.svg
fabric_jumpstart/ui_assets/data_science_24_color.svg
fabric_jumpstart/ui_assets/data_warehouse_24_color.svg
fabric_jumpstart/ui_assets/databases_24_color.svg
fabric_jumpstart/ui_assets/one_lake_24_color.svg
fabric_jumpstart/ui_assets/power_bi_24_color.svg
fabric_jumpstart/ui_assets/real_time_intelligence_24_color.svg
fabric_jumpstart-0.1.0.dist-info/METADATA
fabric_jumpstart-0.1.0.dist-info/WHEEL
fabric_jumpstart-0.1.0.dist-info/licenses/LICENSE
fabric_jumpstart-0.1.0.dist-info/RECORD
