Metadata-Version: 2.4
Name: fabric-jumpstart
Version: 0.1.0
Summary: Get started quickly with pre-built solutions, tutorials, demos, and accelerators—automated, high-quality, and open-source.
Project-URL: Repository, https://github.com/microsoft/fabric-jumpstart.git
Author: Microsoft Corporation
License-Expression: MIT
License-File: LICENSE
Classifier: Programming Language :: Python
Classifier: Programming Language :: Python :: 3.10
Classifier: Programming Language :: Python :: 3.11
Classifier: Programming Language :: Python :: 3.12
Requires-Python: <3.13,>=3.10
Requires-Dist: fabric-cicd==0.1.34
Requires-Dist: ipython>=8.20.0
Requires-Dist: pyyaml>=6.0.3
